phased_array/__init__.py
phased_array/beamforming.py
phased_array/core.py
phased_array/export.py
phased_array/geometry.py
phased_array/impairments.py
phased_array/utils.py
phased_array/visualization.py
phased_array/wideband.py
phased_array_modeling-1.2.0.dist-info/licenses/LICENSE
phased_array_modeling-1.2.0.dist-info/METADATA
phased_array_modeling-1.2.0.dist-info/WHEEL
phased_array_modeling-1.2.0.dist-info/top_level.txt
phased_array_modeling-1.2.0.dist-info/RECORD
